streamsx/pmml/__init__.py
streamsx/pmml/_pmml.py
streamsx.pmml-1.0.7.dist-info/LICENSE.txt
streamsx.pmml-1.0.7.dist-info/METADATA
streamsx.pmml-1.0.7.dist-info/WHEEL
streamsx.pmml-1.0.7.dist-info/top_level.txt
streamsx.pmml-1.0.7.dist-info/RECORD
